BiteAWX/__init__.py
BiteAWX/containers.py
BiteAWX/core.py
BiteAWX/tools.py
BiteAWX-1.0.0.dist-info/LICENSE
BiteAWX-1.0.0.dist-info/METADATA
BiteAWX-1.0.0.dist-info/WHEEL
BiteAWX-1.0.0.dist-info/top_level.txt
BiteAWX-1.0.0.dist-info/RECORD
