Metadata-Version: 2.1
Name: BiteAWX
Version: 1.0.0
Summary: For reading AWX format data.
Author-email: modabao <mo_dabao@qq.com>
Project-URL: repository, https://github.com/Mo-Dabao/BiteAWX.git
Classifier: License :: OSI Approved :: GNU Affero General Public License v3
Requires-Python: >=3.6
License-File: LICENSE
Requires-Dist: numpy
Requires-Dist: xarray
Requires-Dist: pyproj
Requires-Dist: pillow
Requires-Dist: netCDF4
